README
setup.py
run/__init__.py
run/alone.py
run/base.py
run/lock.py
run/time.py
run.egg-info/PKG-INFO
run.egg-info/SOURCES.txt
run.egg-info/dependency_links.txt
run.egg-info/top_level.txt