Metadata-Version: 1.0
Name: run
Version: 0.1
Summary: Python Process Run Control
Home-page: http://freecode.nl/~maze/python-run/
Author: Wijnand Modderman
Author-email: maze@pyth0n.org
License: MIT
Platform: UNKNOWN
